pyp2spec/__init__.py
pyp2spec/classifiers_to_fedora.json
pyp2spec/conf2spec.py
pyp2spec/license_processor.py
pyp2spec/local_loaders.py
pyp2spec/pyp2conf.py
pyp2spec/pyp2spec.py
pyp2spec/pypi_loaders.py
pyp2spec/rpmversion.py
pyp2spec/template.spec
pyp2spec/utils.py
pyp2spec-0.13.0.dist-info/licenses/LICENSE-MIT
pyp2spec-0.13.0.dist-info/licenses/LICENSE-MIT-0
pyp2spec-0.13.0.dist-info/METADATA
pyp2spec-0.13.0.dist-info/WHEEL
pyp2spec-0.13.0.dist-info/entry_points.txt
pyp2spec-0.13.0.dist-info/top_level.txt
pyp2spec-0.13.0.dist-info/RECORD
