Metadata-Version: 2.4
Name: pyp2spec
Version: 0.13.0
Summary: Generate a valid Fedora specfile from Python package from PyPI
Author-email: Karolina Surma <ksurma@redhat.com>
License-Expression: MIT AND MIT-0
Project-URL: homepage, https://github.com/befeleme/pyp2spec/
Classifier: Programming Language :: Python :: 3
Classifier: Programming Language :: Python :: 3.9
Classifier: Programming Language :: Python :: 3.10
Classifier: Programming Language :: Python :: 3.11
Classifier: Programming Language :: Python :: 3.12
Classifier: Programming Language :: Python :: 3.13
Classifier: Programming Language :: Python :: 3.14
Classifier: Operating System :: POSIX :: Linux
Classifier: Development Status :: 3 - Alpha
Requires-Python: >=3.9
License-File: LICENSE-MIT
License-File: LICENSE-MIT-0
Requires-Dist: click
Requires-Dist: jinja2
Requires-Dist: license-expression
Requires-Dist: packaging>=24.2
Requires-Dist: requests
Requires-Dist: tomli; python_version < "3.11"
Requires-Dist: tomli-w
Provides-Extra: test
Requires-Dist: pytest; extra == "test"
Requires-Dist: pytest-regressions; extra == "test"
Requires-Dist: betamax; extra == "test"
Dynamic: license-file
